{
    "about_bio_jp": "私は現在、大阪のECCコンピュータ専門学校でシステムエンジニアコースを学んでいる留学生です。多文化な環境で育った経験を活かしながら、HTML、CSSとJavaScriptを使ったWeb開発に取り組んでいます。使いやすくて見やすい、レスポンシブなWebサイトを作るために、日々スキルを磨いています。最近は、AIや最新のソフトウェアツールについても学びを広げており、より幅広い分野に挑戦していきたいと考えています。クリーンで実用的なデジタル体験を形にしながら、柔軟でクリエイティブなWeb開発者として成長していくことを目指しています。",
    "プロジェクト1": "ECサイト開発",
    "プロジェクト2": "モバイルタスク管理",
    "プロジェクト3": "レシピ共有アプリ",
    "プロジェクト4": "ポートフォリオサイトV1",
    "プロジェクト5": "データ可視化ダッシュボード",
    "メール：": "メール：",
    "電話：": "電話：",
    "GitHub:": "GitHub:",
    "履歴書をダウンロード": "履歴書をダウンロード",
    "あなたの名前. 無断転載を禁じます。": "あなたの名前. 無断転載を禁じます。",
    "こんにちは、私は": "こんにちは、私は",
    "あなたのフルネーム": "あなたのフルネーム",
    "情熱的な開発者＆問題解決者": "情熱的な開発者＆問題解決者",
    "私のポートフォリオへようこそ！ここでは、開発者としての私のプロジェクト、スキル、そして道のりを垣間見ることができます。": "私のポートフォリオへようこそ！ここでは、開発者としての私のプロジェクト、スキル、そして道のりを垣間見ることができます。",
    "私について": "私について",
    "スキル": "スキル",
    "HTML / CSS": "HTML / CSS",
    "Java": "Java",
    "データベース管理": "データベース管理",
    "レスポンシブデザイン": "レスポンシブデザイン",
    "Gitバージョン管理": "Gitバージョン管理",
    "言語能力": "言語能力",
    "日本語": "日本語",
    "JLPT N2認定": "JLPT N2認定",
    "英語": "英語",
    "流暢": "流暢",
    "ミャンマー語": "ミャンマー語",
    "母語": "母語",
    "ネパール語": "ネパール語",
    "ヒンディー語": "ヒンディー語",
    "中級": "中級",
    "プロジェクト": "プロジェクト",
    "私のYouTubeビデオ": "私のYouTubeビデオ",
    "連絡先": "連絡先"
}